processcdf/processcdf/__init__.py
processcdf/processcdf/joinKpcdf.py
processcdf/processcdf/json2hdf.py
processcdf/processcdf/merge_cdf.py
processcdf/processcdf/sep2bins.py
processcdf/pyproject.toml
processcdf/README.md
processcdf/tests/__init__.py
processcdf-0.1.2.dist-info/LICENSE
processcdf-0.1.2.dist-info/METADATA
processcdf-0.1.2.dist-info/WHEEL
processcdf-0.1.2.dist-info/RECORD
