Metadata-Version: 2.1
Name: processcdf
Version: 0.1.2
Summary: DMSP Mission CDF File Converter
Author: ViktoriaMi
Author-email: miheykoviktoria@yandex.ru
Requires-Python: >=3.11,<4.0
Classifier: Programming Language :: Python :: 3
Classifier: Programming Language :: Python :: 3.11
Classifier: Programming Language :: Python :: 3.12
